[
  {
    "firstName": "Danny",
    "lastName": "Simmons",
    "email": "joshuapatterson@yahoo.com",
    "gender": "Male",
    "dob": "2005-09-05",
    "course": "Business Administration",
    "year": 2,
    "gpa": 2.47,
    "enrollmentStatus": "Active"
  },
  {
    "firstName": "Christopher",
    "lastName": "Townsend",
    "email": "william94@gmail.com",
    "gender": "Male",
    "dob": "2004-08-07",
    "course": "Information Technology",
    "year": 4,
    "gpa": 3.04,
    "enrollmentStatus": "Active"
  },
  {
    "firstName": "Nathaniel",
    "lastName": "Mosley",
    "email": "hrussell@gmail.com",
    "gender": "Female",
    "dob": "2003-05-13",
    "course": "Electrical Engineering",
    "year": 3,
    "gpa": 3.69,
    "enrollmentStatus": "Inactive"
  },
  {
    "firstName": "Donald",
    "lastName": "Norris",
    "email": "ebarnett@yahoo.com",
    "gender": "Male",
    "dob": "2005-09-11",
    "course": "Information Technology",
    "year": 4,
    "gpa": 2.14,
    "enrollmentStatus": "Inactive"
  },
  {
    "firstName": "Jessica",
    "lastName": "Nelson",
    "email": "sherrymoreno@gmail.com",
    "gender": "Male",
    "dob": "2005-06-03",
    "course": "Physics",
    "year": 4,
    "gpa": 3.75,
    "enrollmentStatus": "Active"
  },
  {
    "firstName": "Patrick",
    "lastName": "Gray",
    "email": "thomasfarmer@hotmail.com",
    "gender": "Male",
    "dob": "2002-11-15",
    "course": "Economics",
    "year": 1,
    "gpa": 3.61,
    "enrollmentStatus": "Inactive"
  },
  {
    "firstName": "Michael",
    "lastName": "Crosby",
    "email": "oward@hotmail.com",
    "gender": "Female",
    "dob": "2002-08-17",
    "course": "Information Technology",
    "year": 1,
    "gpa": 2.95,
    "enrollmentStatus": "Inactive"
  },
  {
    "firstName": "Richard",
    "lastName": "Santos",
    "email": "nathansteele@gmail.com",
    "gender": "Female",
    "dob": "2003-04-22",
    "course": "Biotechnology",
    "year": 1,
    "gpa": 2.51,
    "enrollmentStatus": "Inactive"
  },
  {
    "firstName": "Shannon",
    "lastName": "Washington",
    "email": "victorcameron@gmail.com",
    "gender": "Female",
    "dob": "2006-02-18",
    "course": "Business Administration",
    "year": 2,
    "gpa": 2.88,
    "enrollmentStatus": "Active"
  },
  {
    "firstName": "David",
    "lastName": "Smith",
    "email": "tanyacummings@moore.com",
    "gender": "Female",
    "dob": "2004-10-29",
    "course": "Mathematics",
    "year": 3,
    "gpa": 3.27,
    "enrollmentStatus": "Inactive"
  },
  {
    "firstName": "Nicholas",
    "lastName": "Flores",
    "email": "ykennedy@hotmail.com",
    "gender": "Female",
    "dob": "2004-04-06",
    "course": "Biotechnology",
    "year": 4,
    "gpa": 2.46,
    "enrollmentStatus": "Inactive"
  },
  {
    "firstName": "Mary",
    "lastName": "Dickerson",
    "email": "xmueller@gmail.com",
    "gender": "Female",
    "dob": "2008-03-13",
    "course": "Physics",
    "year": 3,
    "gpa": 3.74,
    "enrollmentStatus": "Inactive"
  },
  {
    "firstName": "Chad",
    "lastName": "Doyle",
    "email": "jennifer45@yahoo.com",
    "gender": "Female",
    "dob": "2005-05-12",
    "course": "Computer Science",
    "year": 3,
    "gpa": 3.1,
    "enrollmentStatus": "Inactive"
  },
  {
    "firstName": "Tanya",
    "lastName": "Watson",
    "email": "apeters@hotmail.com",
    "gender": "Female",
    "dob": "2004-08-28",
    "course": "Computer Science",
    "year": 4,
    "gpa": 3.26,
    "enrollmentStatus": "Inactive"
  },
  {
    "firstName": "Julie",
    "lastName": "Hernandez",
    "email": "cody17@gmail.com",
    "gender": "Male",
    "dob": "2007-12-24",
    "course": "Physics",
    "year": 3,
    "gpa": 3.68,
    "enrollmentStatus": "Active"
  },
  {
    "firstName": "Nathan",
    "lastName": "Moran",
    "email": "beanchristina@hotmail.com",
    "gender": "Male",
    "dob": "2006-07-14",
    "course": "Civil Engineering",
    "year": 4,
    "gpa": 3.2,
    "enrollmentStatus": "Active"
  },
  {
    "firstName": "Monique",
    "lastName": "Rodriguez",
    "email": "pam24@hernandez-tanner.org",
    "gender": "Female",
    "dob": "2004-10-05",
    "course": "Information Technology",
    "year": 3,
    "gpa": 2.51,
    "enrollmentStatus": "Inactive"
  },
  {
    "firstName": "Brendan",
    "lastName": "Riggs",
    "email": "hjimenez@gmail.com",
    "gender": "Female",
    "dob": "2006-03-14",
    "course": "Mechanical Engineering",
    "year": 3,
    "gpa": 3.74,
    "enrollmentStatus": "Inactive"
  },
  {
    "firstName": "Anthony",
    "lastName": "Davis",
    "email": "jennifer38@gmail.com",
    "gender": "Female",
    "dob": "2004-11-20",
    "course": "Physics",
    "year": 2,
    "gpa": 2.64,
    "enrollmentStatus": "Active"
  },
  {
    "firstName": "Jessica",
    "lastName": "Barker",
    "email": "gbrown@ryan.com",
    "gender": "Male",
    "dob": "2005-01-13",
    "course": "Physics",
    "year": 3,
    "gpa": 2.14,
    "enrollmentStatus": "Inactive"
  },
  {
    "firstName": "Angela",
    "lastName": "Brown",
    "email": "sylvianichols@hotmail.com",
    "gender": "Female",
    "dob": "2003-12-16",
    "course": "Mathematics",
    "year": 2,
    "gpa": 3.42,
    "enrollmentStatus": "Active"
  },
  {
    "firstName": "Valerie",
    "lastName": "Dixon",
    "email": "susan87@perry-owens.com",
    "gender": "Female",
    "dob": "2006-02-10",
    "course": "Economics",
    "year": 3,
    "gpa": 2.58,
    "enrollmentStatus": "Inactive"
  },
  {
    "firstName": "Richard",
    "lastName": "Rose",
    "email": "ydavis@hotmail.com",
    "gender": "Male",
    "dob": "2005-07-02",
    "course": "Electrical Engineering",
    "year": 4,
    "gpa": 2.23,
    "enrollmentStatus": "Inactive"
  },
  {
    "firstName": "Julia",
    "lastName": "Rich",
    "email": "amanda38@wilson.info",
    "gender": "Female",
    "dob": "2005-03-21",
    "course": "Economics",
    "year": 4,
    "gpa": 2.78,
    "enrollmentStatus": "Active"
  },
  {
    "firstName": "Lynn",
    "lastName": "Oconnor",
    "email": "shawnfarley@hotmail.com",
    "gender": "Female",
    "dob": "2005-10-24",
    "course": "Biotechnology",
    "year": 2,
    "gpa": 3.89,
    "enrollmentStatus": "Inactive"
  },
  {
    "firstName": "Joshua",
    "lastName": "Richmond",
    "email": "shenderson@hotmail.com",
    "gender": "Male",
    "dob": "2007-11-19",
    "course": "Computer Science",
    "year": 4,
    "gpa": 4.0,
    "enrollmentStatus": "Active"
  },
  {
    "firstName": "Rachel",
    "lastName": "Tran",
    "email": "heather36@hawkins.com",
    "gender": "Male",
    "dob": "2003-11-19",
    "course": "Physics",
    "year": 1,
    "gpa": 2.74,
    "enrollmentStatus": "Inactive"
  },
  {
    "firstName": "Kimberly",
    "lastName": "Cooper",
    "email": "baileydavis@yahoo.com",
    "gender": "Female",
    "dob": "2007-08-26",
    "course": "Civil Engineering",
    "year": 3,
    "gpa": 2.92,
    "enrollmentStatus": "Inactive"
  },
  {
    "firstName": "Annette",
    "lastName": "Poole",
    "email": "singhmatthew@yahoo.com",
    "gender": "Male",
    "dob": "2004-12-21",
    "course": "Biotechnology",
    "year": 3,
    "gpa": 3.83,
    "enrollmentStatus": "Inactive"
  },
  {
    "firstName": "Edward",
    "lastName": "Woodward",
    "email": "grayedward@hotmail.com",
    "gender": "Female",
    "dob": "2007-06-02",
    "course": "Physics",
    "year": 2,
    "gpa": 3.89,
    "enrollmentStatus": "Inactive"
  },
  {
    "firstName": "Anthony",
    "lastName": "Wilson",
    "email": "gabriela34@thompson-contreras.org",
    "gender": "Female",
    "dob": "2007-05-11",
    "course": "Mathematics",
    "year": 3,
    "gpa": 3.99,
    "enrollmentStatus": "Inactive"
  },
  {
    "firstName": "Joshua",
    "lastName": "Daniels",
    "email": "holly51@bean.com",
    "gender": "Female",
    "dob": "2007-04-19",
    "course": "Biotechnology",
    "year": 2,
    "gpa": 2.03,
    "enrollmentStatus": "Active"
  },
  {
    "firstName": "Elizabeth",
    "lastName": "Hubbard",
    "email": "qmelendez@wade-walton.org",
    "gender": "Female",
    "dob": "2002-08-11",
    "course": "Electrical Engineering",
    "year": 1,
    "gpa": 3.66,
    "enrollmentStatus": "Active"
  },
  {
    "firstName": "Dillon",
    "lastName": "Armstrong",
    "email": "jwest@hardy-martinez.net",
    "gender": "Female",
    "dob": "2004-07-14",
    "course": "Civil Engineering",
    "year": 1,
    "gpa": 3.12,
    "enrollmentStatus": "Active"
  },
  {
    "firstName": "Mary",
    "lastName": "Scott",
    "email": "robertblackwell@yahoo.com",
    "gender": "Female",
    "dob": "2008-01-14",
    "course": "Business Administration",
    "year": 1,
    "gpa": 3.59,
    "enrollmentStatus": "Inactive"
  },
  {
    "firstName": "Tina",
    "lastName": "Smith",
    "email": "lauriemartinez@hotmail.com",
    "gender": "Female",
    "dob": "2008-04-02",
    "course": "Civil Engineering",
    "year": 4,
    "gpa": 2.12,
    "enrollmentStatus": "Inactive"
  },
  {
    "firstName": "Barbara",
    "lastName": "Bowen",
    "email": "ritterlaura@perez.com",
    "gender": "Male",
    "dob": "2005-03-24",
    "course": "Physics",
    "year": 2,
    "gpa": 2.83,
    "enrollmentStatus": "Inactive"
  },
  {
    "firstName": "Travis",
    "lastName": "Anderson",
    "email": "lbrown@hotmail.com",
    "gender": "Male",
    "dob": "2003-10-28",
    "course": "Business Administration",
    "year": 3,
    "gpa": 3.86,
    "enrollmentStatus": "Inactive"
  },
  {
    "firstName": "Mandy",
    "lastName": "Long",
    "email": "smithjulie@cooper.com",
    "gender": "Female",
    "dob": "2002-05-18",
    "course": "Electrical Engineering",
    "year": 3,
    "gpa": 3.85,
    "enrollmentStatus": "Active"
  },
  {
    "firstName": "Carolyn",
    "lastName": "Guerra",
    "email": "jessicapaul@franklin-cook.com",
    "gender": "Female",
    "dob": "2002-10-31",
    "course": "Mathematics",
    "year": 1,
    "gpa": 2.15,
    "enrollmentStatus": "Inactive"
  },
  {
    "firstName": "Jennifer",
    "lastName": "Nolan",
    "email": "johnflores@hotmail.com",
    "gender": "Male",
    "dob": "2006-09-09",
    "course": "Physics",
    "year": 4,
    "gpa": 2.72,
    "enrollmentStatus": "Inactive"
  },
  {
    "firstName": "Kristen",
    "lastName": "Howard",
    "email": "phillipsjeanne@adams.net",
    "gender": "Female",
    "dob": "2003-10-11",
    "course": "Computer Science",
    "year": 4,
    "gpa": 2.04,
    "enrollmentStatus": "Active"
  },
  {
    "firstName": "Shannon",
    "lastName": "Morales",
    "email": "vwarren@yahoo.com",
    "gender": "Female",
    "dob": "2002-05-28",
    "course": "Information Technology",
    "year": 2,
    "gpa": 2.21,
    "enrollmentStatus": "Active"
  },
  {
    "firstName": "Mary",
    "lastName": "Knight",
    "email": "elizabethjensen@smith.biz",
    "gender": "Female",
    "dob": "2005-04-18",
    "course": "Civil Engineering",
    "year": 1,
    "gpa": 2.69,
    "enrollmentStatus": "Inactive"
  },
  {
    "firstName": "Brandon",
    "lastName": "Kim",
    "email": "zhangdavid@gmail.com",
    "gender": "Female",
    "dob": "2005-08-01",
    "course": "Mechanical Engineering",
    "year": 2,
    "gpa": 2.09,
    "enrollmentStatus": "Active"
  },
  {
    "firstName": "Yolanda",
    "lastName": "Young",
    "email": "daniellerobinson@hotmail.com",
    "gender": "Female",
    "dob": "2005-04-10",
    "course": "Information Technology",
    "year": 2,
    "gpa": 3.35,
    "enrollmentStatus": "Active"
  },
  {
    "firstName": "Darryl",
    "lastName": "Warren",
    "email": "yolandahernandez@edwards.com",
    "gender": "Male",
    "dob": "2007-05-28",
    "course": "Electrical Engineering",
    "year": 2,
    "gpa": 3.2,
    "enrollmentStatus": "Active"
  },
  {
    "firstName": "Sean",
    "lastName": "Brown",
    "email": "jefferycarter@dean-hudson.net",
    "gender": "Male",
    "dob": "2005-07-07",
    "course": "Physics",
    "year": 2,
    "gpa": 3.51,
    "enrollmentStatus": "Inactive"
  },
  {
    "firstName": "Patricia",
    "lastName": "Thomas",
    "email": "christopher78@yahoo.com",
    "gender": "Male",
    "dob": "2007-09-04",
    "course": "Civil Engineering",
    "year": 1,
    "gpa": 3.99,
    "enrollmentStatus": "Active"
  },
  {
    "firstName": "George",
    "lastName": "Nelson",
    "email": "katherine75@wong-riley.org",
    "gender": "Female",
    "dob": "2004-11-23",
    "course": "Computer Science",
    "year": 2,
    "gpa": 3.9,
    "enrollmentStatus": "Active"
  }
]